libephemeris/__init__.py
libephemeris/angles.py
libephemeris/arabic_parts.py
libephemeris/astropy_integration.py
libephemeris/cache.py
libephemeris/constants.py
libephemeris/context.py
libephemeris/crossing.py
libephemeris/eclipse.py
libephemeris/erfa_nutation.py
libephemeris/exceptions.py
libephemeris/extinction.py
libephemeris/fixed_stars.py
libephemeris/heliacal.py
libephemeris/houses.py
libephemeris/hypothetical.py
libephemeris/iers_data.py
libephemeris/lunar.py
libephemeris/minor_bodies.py
libephemeris/planetary_moons.py
libephemeris/planets.py
libephemeris/profiling.py
libephemeris/py.typed
libephemeris/rebound_integration.py
libephemeris/seorbel.txt
libephemeris/spk.py
libephemeris/spk_auto.py
libephemeris/state.py
libephemeris/time_utils.py
libephemeris/true_node_terms.py
libephemeris/utils.py
libephemeris-0.4.0.dist-info/licenses/LICENSE
libephemeris-0.4.0.dist-info/METADATA
libephemeris-0.4.0.dist-info/WHEEL
libephemeris-0.4.0.dist-info/top_level.txt
libephemeris-0.4.0.dist-info/RECORD
