Metadata-Version: 2.4
Name: libephemeris
Version: 0.4.0
Summary: A high-precision, open-source astronomical ephemeris library for Python, powered by Skyfield.
Author-email: Giacomo Battaglia <giacomo@libephemeris.dev>
Maintainer-email: Giacomo Battaglia <giacomo@libephemeris.dev>
License-Expression: LGPL-3.0-only
Project-URL: Homepage, https://github.com/g-battaglia/libephemeris
Project-URL: Documentation, https://github.com/g-battaglia/libephemeris#readme
Project-URL: Repository, https://github.com/g-battaglia/libephemeris
Project-URL: Issues, https://github.com/g-battaglia/libephemeris/issues
Project-URL: Changelog, https://github.com/g-battaglia/libephemeris/blob/main/CHANGELOG.md
Keywords: astronomy,ephemeris,astrology,planetary,skyfield,swiss-ephemeris,astrological,celestial,horoscope,zodiac
Classifier: Development Status :: 2 - Pre-Alpha
Classifier: Intended Audience :: Science/Research
Classifier: Intended Audience :: Developers
Classifier: Intended Audience :: Education
Classifier: Operating System :: OS Independent
Classifier: Programming Language :: Python :: 3
Classifier: Programming Language :: Python :: 3.9
Classifier: Programming Language :: Python :: 3.10
Classifier: Programming Language :: Python :: 3.11
Classifier: Programming Language :: Python :: 3.12
Classifier: Programming Language :: Python :: 3.13
Classifier: Topic :: Scientific/Engineering :: Astronomy
Classifier: Topic :: Scientific/Engineering :: Physics
Classifier: Typing :: Typed
Requires-Python: >=3.9
License-File: LICENSE
Requires-Dist: skyfield>=1.54
Requires-Dist: skyfield-data>=7.0.0
Provides-Extra: precision
Requires-Dist: pyerfa>=2.0.0; extra == "precision"
Provides-Extra: spk
Requires-Dist: astroquery>=0.4.0; extra == "spk"
Provides-Extra: stars
Requires-Dist: astroquery>=0.4.0; extra == "stars"
Requires-Dist: astropy>=5.0.0; extra == "stars"
Provides-Extra: nbody
Requires-Dist: rebound>=4.0.0; extra == "nbody"
Requires-Dist: assist>=1.1.0; extra == "nbody"
Provides-Extra: all
Requires-Dist: pyerfa>=2.0.0; extra == "all"
Requires-Dist: astroquery>=0.4.0; extra == "all"
Requires-Dist: rebound>=4.0.0; extra == "all"
Requires-Dist: assist>=1.1.0; extra == "all"
Provides-Extra: dev
Requires-Dist: black>=25.1.0; extra == "dev"
Requires-Dist: mypy>=1.0.0; extra == "dev"
Requires-Dist: poethepoet>=0.38.0; extra == "dev"
Requires-Dist: pre-commit>=4.0.0; extra == "dev"
Requires-Dist: pyswisseph>=2.10.3.2; extra == "dev"
Requires-Dist: pytest>=9.0.1; extra == "dev"
Requires-Dist: pytest-xdist>=3.5.0; extra == "dev"
Requires-Dist: ruff>=0.14.6; extra == "dev"
Requires-Dist: pytest-cov>=6.0.0; extra == "dev"
Requires-Dist: build>=1.0.0; extra == "dev"
Requires-Dist: twine>=5.0.0; extra == "dev"
Requires-Dist: pytest-sugar>=1.1.1; extra == "dev"
Provides-Extra: docs
Requires-Dist: sphinx>=7.0.0; extra == "docs"
Requires-Dist: sphinx-rtd-theme>=2.0.0; extra == "docs"
Requires-Dist: myst-parser>=2.0.0; extra == "docs"
Dynamic: license-file
